nlogin_py/__init__.py
nlogin_py/nlogin.py
nlogin_py/algorithms/__init__.py
nlogin_py/algorithms/algorithm.py
nlogin_py/algorithms/authme.py
nlogin_py/algorithms/bcrypt.py
nlogin_py/algorithms/sha256.py
nlogin_py/algorithms/sha512.py
nlogin_py-1.0.0.dist-info/METADATA
nlogin_py-1.0.0.dist-info/WHEEL
nlogin_py-1.0.0.dist-info/top_level.txt
nlogin_py-1.0.0.dist-info/RECORD
