Metadata-Version: 2.1
Name: nlogin_py
Version: 1.0.0
Summary: A package for interacting with the nLogin plugin
Home-page: https://github.com/Shandeika/nlogin_py
Author: MrShandy
Author-email: mrshandy@shandy.dev
License: GPL-3.0
Classifier: Programming Language :: Python :: 3.10
Classifier: License :: OSI Approved :: GNU General Public License v3 (GPLv3)
Classifier: Operating System :: Microsoft :: Windows
Classifier: Operating System :: POSIX :: Linux
Classifier: Topic :: Software Development :: Libraries :: Python Modules
Requires-Dist: pymysql ~=1.1.1
Requires-Dist: bcrypt ~=3.2.0
